lulzurl/__init__.py
lulzurl/easyurl.py
lulzurl-0.0.1.dist-info/METADATA
lulzurl-0.0.1.dist-info/WHEEL
lulzurl-0.0.1.dist-info/licenses/LICENSE
lulzurl-0.0.1.dist-info/RECORD
